deepcore_server/__init__.py
deepcore_server/api_client.py
deepcore_server/configuration.py
deepcore_server/rest.py
deepcore_server/api/__init__.py
deepcore_server/api/config_api.py
deepcore_server/api/job_api.py
deepcore_server/api/model_api.py
deepcore_server/api/runner_api.py
deepcore_server/models/__init__.py
deepcore_server/models/color_mode.py
deepcore_server/models/created_message.py
deepcore_server/models/deleted_message.py
deepcore_server/models/error.py
deepcore_server/models/id_list.py
deepcore_server/models/image.py
deepcore_server/models/inline_response200.py
deepcore_server/models/job_request.py
deepcore_server/models/job_status.py
deepcore_server/models/label_filter.py
deepcore_server/models/lat_lon_bounding_box.py
deepcore_server/models/lat_lon_coord.py
deepcore_server/models/message.py
deepcore_server/models/model_metadata.py
deepcore_server/models/point.py
deepcore_server/models/r2_p_properties.py
deepcore_server/models/runner_request.py
deepcore_server/models/runner_status.py
deepcore_server/models/service_version.py
deepcore_server/models/size.py
deepcore_server/models/size_step.py
deepcore_server/models/version.py
test/__init__.py
test/test_color_mode.py
test/test_config_api.py
test/test_created_message.py
test/test_deleted_message.py
test/test_error.py
test/test_id_list.py
test/test_image.py
test/test_inline_response200.py
test/test_job_api.py
test/test_job_request.py
test/test_job_status.py
test/test_label_filter.py
test/test_lat_lon_bounding_box.py
test/test_lat_lon_coord.py
test/test_message.py
test/test_model_api.py
test/test_model_metadata.py
test/test_point.py
test/test_r2_p_properties.py
test/test_runner_api.py
test/test_runner_request.py
test/test_runner_status.py
test/test_service_version.py
test/test_size.py
test/test_size_step.py
test/test_version.py
deepcore_server-1.3.2.1.dist-info/METADATA
deepcore_server-1.3.2.1.dist-info/WHEEL
deepcore_server-1.3.2.1.dist-info/top_level.txt
deepcore_server-1.3.2.1.dist-info/RECORD
