Metadata-Version: 2.1
Name: deepcore-server
Version: 1.3.2.1
Summary: DeepCore Server
Home-page: http://deepcore.io
Author: UNKNOWN
Author-email: deepcore-support@digitalglobe.com
License: Apache License, Version 2.0
Keywords: Swagger,DeepCore Server
Platform: UNKNOWN
Requires-Dist: urllib3 (>=1.15)
Requires-Dist: six (>=1.10)
Requires-Dist: certifi
Requires-Dist: python-dateutil
